pymqtt/__init__.py
pymqtt-0.0.7.dist-info/LICENSE
pymqtt-0.0.7.dist-info/METADATA
pymqtt-0.0.7.dist-info/WHEEL
pymqtt-0.0.7.dist-info/top_level.txt
pymqtt-0.0.7.dist-info/zip-safe
pymqtt-0.0.7.dist-info/RECORD
