Metadata-Version: 2.1
Name: pymqtt
Version: 0.0.7
Summary: Adds pymqtt support to your Python application.
Home-page: https://github.com/flask-rabmq/pymqtt
Author: chenxiaolong
Author-email: cxiaolong6@gmail.com
License: MIT
Keywords: python flask django mqtt
Platform: UNKNOWN
Classifier: License :: OSI Approved :: MIT License
Classifier: Programming Language :: Python
Classifier: Intended Audience :: Developers
Classifier: Operating System :: OS Independent
Requires-Python: >=2.7, !=3.0.*, !=3.1.*, !=3.2.*, !=3.3.*, !=3.4.*, !=3.5.*
Requires-Dist: paho-mqtt (>=1.4.0)
